stooqpy/__init__.py
stooqpy/__main__.py
stooqpy/cli.py
stooqpy/config.py
stooqpy/templates/settings.py
stooqpy/templates/setup.yaml
stooqpy-0.0.7.dist-info/licenses/LICENSE
stooqpy-0.0.7.dist-info/METADATA
stooqpy-0.0.7.dist-info/WHEEL
stooqpy-0.0.7.dist-info/entry_points.txt
stooqpy-0.0.7.dist-info/top_level.txt
stooqpy-0.0.7.dist-info/RECORD
