Metadata-Version: 2.4
Name: stooqpy
Version: 0.0.7
Summary: Automatyzuje pobieranie wysokiej jakości darmowych danych z serwisu stooq.pl.
Author-email: Szymon Jan Marek <szymon.jan.marek@gmail.com>
License: MIT
Project-URL: bugs, https://github.com/neon-symeon/stooqpy/issues
Project-URL: changelog, https://github.com/neon-symeon/stooqpy/blob/master/changelog.md
Project-URL: homepage, https://github.com/neon-symeon/stooqpy
Classifier: Development Status :: 3 - Alpha
Classifier: Intended Audience :: Developers
Classifier: Intended Audience :: Financial and Insurance Industry
Classifier: Intended Audience :: Education
Classifier: License :: OSI Approved :: MIT License
Classifier: Programming Language :: Python :: 3 :: Only
Classifier: Programming Language :: Python :: 3.10
Classifier: Programming Language :: Python :: 3.11
Classifier: Programming Language :: Python :: 3.12
Classifier: Programming Language :: Python :: 3.13
Classifier: Operating System :: OS Independent
Classifier: Topic :: Software Development :: Libraries :: Python Modules
Classifier: Topic :: Office/Business :: Financial :: Investment
Requires-Python: >=3.8
License-File: LICENSE
Requires-Dist: typer
Requires-Dist: platformdirs
Requires-Dist: ruamel.yaml
Provides-Extra: test
Requires-Dist: coverage; extra == "test"
Requires-Dist: pytest; extra == "test"
Requires-Dist: ruff; extra == "test"
Requires-Dist: ty; extra == "test"
Requires-Dist: ipdb; extra == "test"
Dynamic: license-file
